{
    "order_date": "25Oct",
    "optm_id": "000000000002",
    "result": [
        {
            "CAR_NUM": "CE07",
            "VISIT_ORDER": 4,
            "Y": 1.303583,
            "X": 103.841268,
            "ADDRESS_FULL": "03-08, 63, Cavenagh Road 229618",
            "ZIP_CODE": "229618",
            "OPT_ARR_TIME_HM": "11:20",
            "EST_PROC_TIME": 7,
            "BOX_NUM": 1,
            "ORDER_VOLUME": 1.557,
            "OPEN_TIME": 600,
            "CLOSE_TIME": 720,
            "NM_COUNT": 1.0,
            "BOX_COUNT": 1.0,
            "PLACE_ID": "ChIJ69M8JZQZ2jERTJGI7KTQIMk"
        },
        {
            "CAR_NUM": "CE07",
            "VISIT_ORDER": 5,
            "Y": 1.3028389999999999,
            "X": 103.840585,
            "ADDRESS_FULL": "51 Cuppage Road #01-01,Singapore,22  Orchard  Cairnhill  River  Valley,51 CUPPAGE ROAD,  229469",
            "ZIP_CODE": "229469",
            "OPT_ARR_TIME_HM": "12:03",
            "EST_PROC_TIME": 9,
            "BOX_NUM": 6,
            "ORDER_VOLUME": 3.042,
            "OPEN_TIME": 780,
            "CLOSE_TIME": 1140,
            "NM_COUNT": 1.0,
            "BOX_COUNT": 6.0,
            "PLACE_ID": "ChIJGflfoZYZ2jER47nhhP6Kx8U"
        },
        {
            "CAR_NUM": "CE07",
            "VISIT_ORDER": 6,
            "Y": 1.311526,
            "X": 103.84224300000001,
            "ADDRESS_FULL": "188 Bukit Timah Road,Singapore,22  Orchard  Cairnhill  River  Valley,188 BUKIT TIMAH ROAD,  229856",
            "ZIP_CODE": "229856",
            "OPT_ARR_TIME_HM": "12:20",
            "EST_PROC_TIME": 9,
            "BOX_NUM": 9,
            "ORDER_VOLUME": 14.013,
            "OPEN_TIME": 720,
            "CLOSE_TIME": 900,
            "NM_COUNT": 1.0,
            "BOX_COUNT": 9.0,
            "PLACE_ID": "ChIJ95R7MeoZ2jERIH1Y5ZkURv0"
        },
        {
            "CAR_NUM": "CE07",
            "VISIT_ORDER": 7,
            "Y": 1.306298,
            "X": 103.837321,
            "ADDRESS_FULL": "53 Cairnhill Road Apt 34-03,  229664",
            "ZIP_CODE": "229664",
            "OPT_ARR_TIME_HM": "12:34",
            "EST_PROC_TIME": 7,
            "BOX_NUM": 1,
            "ORDER_VOLUME": 1.557,
            "OPEN_TIME": 720,
            "CLOSE_TIME": 900,
            "NM_COUNT": 1.0,
            "BOX_COUNT": 1.0,
            "PLACE_ID": "ChIJh1nlEJMZ2jERT7Bx4ihJbLw"
        },
        {
            "CAR_NUM": "CE07",
            "VISIT_ORDER": 8,
            "Y": 1.3072489999999999,
            "X": 103.83335799999999,
            "ADDRESS_FULL": "14 SCOTTS ROAD #03-73,Singapore,22  Orchard  Cairnhill  River  Valley,14 SCOTTS ROAD,  228213",
            "ZIP_CODE": "228213",
            "OPT_ARR_TIME_HM": "12:45",
            "EST_PROC_TIME": 8,
            "BOX_NUM": 5,
            "ORDER_VOLUME": 7.785,
            "OPEN_TIME": 720,
            "CLOSE_TIME": 1140,
            "NM_COUNT": 1.0,
            "BOX_COUNT": 5.0,
            "PLACE_ID": "ChIJL3MQpZIZ2jER8HXwP293Hts"
        },
        {
            "CAR_NUM": "CE07",
            "VISIT_ORDER": 9,
            "Y": 1.3223719999999999,
            "X": 103.81374,
            "ADDRESS_FULL": "10 JALAN SERENE\nSERENE CENTRE\n#02-09,Singapore,25  Ardmore  Bukit  Timah  Holland  Road  Tanglin,10 JALAN SERENE,  258748",
            "ZIP_CODE": "258748",
            "OPT_ARR_TIME_HM": "13:04",
            "EST_PROC_TIME": 10,
            "BOX_NUM": 11,
            "ORDER_VOLUME": 12.452,
            "OPEN_TIME": 720,
            "CLOSE_TIME": 1200,
            "NM_COUNT": 1.0,
            "BOX_COUNT": 11.0,
            "PLACE_ID": "ChIJq9N3HwQa2jERIo7mcKz3ABM"
        },
        {
            "CAR_NUM": "CE09",
            "VISIT_ORDER": 5,
            "Y": 1.302638,
            "X": 103.86222,
            "ADDRESS_FULL": "371 BEACH ROAD CITY GATE, #01-01 (Outside, facing St John's HQ),Singapore,19  Middle  Road  Golden  Mile,371 BEACH ROAD,  199597",
            "ZIP_CODE": "199597",
            "OPT_ARR_TIME_HM": "11:08",
            "EST_PROC_TIME": 12,
            "BOX_NUM": 20,
            "ORDER_VOLUME": 9.46,
            "OPEN_TIME": 660,
            "CLOSE_TIME": 840,
            "NM_COUNT": 1.0,
            "BOX_COUNT": 20.0,
            "PLACE_ID": "ChIJVWCt4LMZ2jEReufwcKz3ABM"
        },
        {
            "CAR_NUM": "CE09",
            "VISIT_ORDER": 6,
            "Y": 1.303492,
            "X": 103.864359,
            "ADDRESS_FULL": "Blk 1 Beach Road #01-4747,Singapore,19  Middle  Road  Golden  Mile,1 BEACH ROAD,  190001",
            "ZIP_CODE": "190001",
            "OPT_ARR_TIME_HM": "12:03",
            "EST_PROC_TIME": 9,
            "BOX_NUM": 6,
            "ORDER_VOLUME": 9.342,
            "OPEN_TIME": 720,
            "CLOSE_TIME": 900,
            "NM_COUNT": 1.0,
            "BOX_COUNT": 6.0,
            "PLACE_ID": "ChIJ1Z0vfLQZ2jERUszzcKz3ABM"
        },
        {
            "CAR_NUM": "CE09",
            "VISIT_ORDER": 7,
            "Y": 1.30386,
            "X": 103.864834,
            "ADDRESS_FULL": "Block 2 Beach Road #01-4803,Singapore,19  Middle  Road  Golden  Mile,2 BEACH ROAD,  190002",
            "ZIP_CODE": "190002",
            "OPT_ARR_TIME_HM": "12:14",
            "EST_PROC_TIME": 9,
            "BOX_NUM": 8,
            "ORDER_VOLUME": 2.28,
            "OPEN_TIME": 720,
            "CLOSE_TIME": 900,
            "NM_COUNT": 1.0,
            "BOX_COUNT": 8.0,
            "PLACE_ID": "ChIJO3O6jrQZ2jERQszzcKz3ABM"
        },
        {
            "CAR_NUM": "CE09",
            "VISIT_ORDER": 8,
            "Y": 1.308384,
            "X": 103.861858,
            "ADDRESS_FULL": "blk 809, #02-33,kitchener complex,french road , singapore 200809,Singapore,20  Little  India,809 FRENCH ROAD,  200809",
            "ZIP_CODE": "200809",
            "OPT_ARR_TIME_HM": "12:27",
            "EST_PROC_TIME": 8,
            "BOX_NUM": 2,
            "ORDER_VOLUME": 3.114,
            "OPEN_TIME": 720,
            "CLOSE_TIME": 900,
            "NM_COUNT": 2.0,
            "BOX_COUNT": 3.0,
            "PLACE_ID": "ChIJKZV8-MkZ2jERKOeov7oRtr0"
        },
        {
            "CAR_NUM": "CE09",
            "VISIT_ORDER": 9,
            "Y": 1.308384,
            "X": 103.861858,
            "ADDRESS_FULL": "809 French Road, #04-152 Glass Door, Kitchener Complex,Singapore,20  Little  India,809 FRENCH ROAD,  200809",
            "ZIP_CODE": "200809",
            "OPT_ARR_TIME_HM": "12:35",
            "EST_PROC_TIME": 7,
            "BOX_NUM": 1,
            "ORDER_VOLUME": 1.557,
            "OPEN_TIME": 720,
            "CLOSE_TIME": 900,
            "NM_COUNT": 2.0,
            "BOX_COUNT": 3.0,
            "PLACE_ID": "ChIJKZV8-MkZ2jERKOeov7oRtr0"
        },
        {
            "CAR_NUM": "CE09",
            "VISIT_ORDER": 10,
            "Y": 1.306227,
            "X": 103.85858,
            "ADDRESS_FULL": "1 SYED ALWI ROAD,Singapore,20  Little  India,1 SYED ALWI ROAD,  207628",
            "ZIP_CODE": "207628",
            "OPT_ARR_TIME_HM": "12:49",
            "EST_PROC_TIME": 9,
            "BOX_NUM": 9,
            "ORDER_VOLUME": 9.342,
            "OPEN_TIME": 720,
            "CLOSE_TIME": 900,
            "NM_COUNT": 1.0,
            "BOX_COUNT": 9.0,
            "PLACE_ID": "ChIJ824pTbYZ2jERmvbkcKz3ABM"
        },
        {
            "CAR_NUM": "CE09",
            "VISIT_ORDER": 11,
            "Y": 1.3059290000000001,
            "X": 103.852845,
            "ADDRESS_FULL": "No 44 Clive Street,Singapore,20  Little  India,44 CLIVE STREET,  209788",
            "ZIP_CODE": "209788",
            "OPT_ARR_TIME_HM": "13:05",
            "EST_PROC_TIME": 8,
            "BOX_NUM": 5,
            "ORDER_VOLUME": 3.745,
            "OPEN_TIME": 720,
            "CLOSE_TIME": 960,
            "NM_COUNT": 1.0,
            "BOX_COUNT": 5.0,
            "PLACE_ID": "ChIJU1x_87gZ2jERbsDFBygTsuQ"
        },
        {
            "CAR_NUM": "CE09",
            "VISIT_ORDER": 12,
            "Y": 1.3105129999999998,
            "X": 103.852791,
            "ADDRESS_FULL": "164 RACE COURSE ROAD,#01-01,Singapore,21  Little  India,164 RACE COURSE ROAD,  218604",
            "ZIP_CODE": "218604",
            "OPT_ARR_TIME_HM": "13:17",
            "EST_PROC_TIME": 8,
            "BOX_NUM": 5,
            "ORDER_VOLUME": 3.805,
            "OPEN_TIME": 780,
            "CLOSE_TIME": 1140,
            "NM_COUNT": 3.0,
            "BOX_COUNT": 21.0,
            "PLACE_ID": "ChIJxxgt-8YZ2jERBI-UvTPHUnE"
        },
        {
            "CAR_NUM": "CE09",
            "VISIT_ORDER": 13,
            "Y": 1.3105129999999998,
            "X": 103.852791,
            "ADDRESS_FULL": "#0301 164 race course road,Singapore,21  Little  India,164 RACE COURSE ROAD,  218604",
            "ZIP_CODE": "218604",
            "OPT_ARR_TIME_HM": "13:25",
            "EST_PROC_TIME": 11,
            "BOX_NUM": 13,
            "ORDER_VOLUME": 20.241,
            "OPEN_TIME": 780,
            "CLOSE_TIME": 1140,
            "NM_COUNT": 3.0,
            "BOX_COUNT": 21.0,
            "PLACE_ID": "ChIJxxgt-8YZ2jERBI-UvTPHUnE"
        },
        {
            "CAR_NUM": "CE09",
            "VISIT_ORDER": 14,
            "Y": 1.3105129999999998,
            "X": 103.852791,
            "ADDRESS_FULL": "#01-01, 164 Race Course Road, 218604 Singapore,Singapore,21  Little  India,164 RACE COURSE ROAD,  218604",
            "ZIP_CODE": "218604",
            "OPT_ARR_TIME_HM": "13:36",
            "EST_PROC_TIME": 8,
            "BOX_NUM": 3,
            "ORDER_VOLUME": 4.293,
            "OPEN_TIME": 780,
            "CLOSE_TIME": 1140,
            "NM_COUNT": 3.0,
            "BOX_COUNT": 21.0,
            "PLACE_ID": "ChIJxxgt-8YZ2jERBI-UvTPHUnE"
        },
        {
            "CAR_NUM": "CE09",
            "VISIT_ORDER": 15,
            "Y": 1.3107440000000001,
            "X": 103.85263499999999,
            "ADDRESS_FULL": "162 RACE COURSE ROAD #03-01,Singapore,21  Little  India,162 RACE COURSE ROAD,  218603",
            "ZIP_CODE": "218603",
            "OPT_ARR_TIME_HM": "13:45",
            "EST_PROC_TIME": 8,
            "BOX_NUM": 3,
            "ORDER_VOLUME": 2.427,
            "OPEN_TIME": 780,
            "CLOSE_TIME": 1200,
            "NM_COUNT": 2.0,
            "BOX_COUNT": 14.0,
            "PLACE_ID": "ChIJ0WZc48YZ2jERVHyXmT9Lzs8"
        },
        {
            "CAR_NUM": "CE09",
            "VISIT_ORDER": 16,
            "Y": 1.3107440000000001,
            "X": 103.85263499999999,
            "ADDRESS_FULL": "162 race course road #01-01,Singapore,21  Little  India,162 RACE COURSE ROAD,  218603",
            "ZIP_CODE": "218603",
            "OPT_ARR_TIME_HM": "13:54",
            "EST_PROC_TIME": 10,
            "BOX_NUM": 11,
            "ORDER_VOLUME": 10.725,
            "OPEN_TIME": 780,
            "CLOSE_TIME": 1200,
            "NM_COUNT": 2.0,
            "BOX_COUNT": 14.0,
            "PLACE_ID": "ChIJ0WZc48YZ2jERVHyXmT9Lzs8"
        },
        {
            "CAR_NUM": "CE09",
            "VISIT_ORDER": 17,
            "Y": 1.310986,
            "X": 103.855056,
            "ADDRESS_FULL": "320, Serangoon Rd Centrium Square, #11-10 218108",
            "ZIP_CODE": "218108",
            "OPT_ARR_TIME_HM": "14:08",
            "EST_PROC_TIME": 8,
            "BOX_NUM": 2,
            "ORDER_VOLUME": 2.728,
            "OPEN_TIME": 840,
            "CLOSE_TIME": 1140,
            "NM_COUNT": 1.0,
            "BOX_COUNT": 2.0,
            "PLACE_ID": "ChIJEwAka8YZ2jERGvLucKz3ABM"
        },
        {
            "CAR_NUM": "CE09",
            "VISIT_ORDER": 18,
            "Y": 1.317048,
            "X": 103.852406,
            "ADDRESS_FULL": "BLK 54 KENT ROAD #20-03,Singapore,21  Little  India,54 KENT ROAD,  210054",
            "ZIP_CODE": "210054",
            "OPT_ARR_TIME_HM": "14:20",
            "EST_PROC_TIME": 7,
            "BOX_NUM": 1,
            "ORDER_VOLUME": 1.0,
            "OPEN_TIME": 840,
            "CLOSE_TIME": 1200,
            "NM_COUNT": 2.0,
            "BOX_COUNT": 7.0,
            "PLACE_ID": "ChIJ98HWzMQZ2jERjO7y5zGjEao"
        },
        {
            "CAR_NUM": "CE09",
            "VISIT_ORDER": 19,
            "Y": 1.317048,
            "X": 103.852406,
            "ADDRESS_FULL": "Kent Road, #20-03,  210054",
            "ZIP_CODE": "210054",
            "OPT_ARR_TIME_HM": "14:27",
            "EST_PROC_TIME": 9,
            "BOX_NUM": 6,
            "ORDER_VOLUME": 1.0,
            "OPEN_TIME": 840,
            "CLOSE_TIME": 1200,
            "NM_COUNT": 2.0,
            "BOX_COUNT": 7.0,
            "PLACE_ID": "ChIJ98HWzMQZ2jERjO7y5zGjEao"
        },
        {
            "CAR_NUM": "CE01",
            "VISIT_ORDER": 7,
            "Y": 1.3159610000000002,
            "X": 103.865179,
            "ADDRESS_FULL": "202 KALLANG BAHRU #03-WPS327,Singapore,33  Balestier  Toa  Payoh  Serangoon,202 KALLANG BAHRU,  339339",
            "ZIP_CODE": "339339",
            "OPT_ARR_TIME_HM": "11:11",
            "EST_PROC_TIME": 14,
            "BOX_NUM": 25,
            "ORDER_VOLUME": 21.95,
            "OPEN_TIME": 600,
            "CLOSE_TIME": 1140,
            "NM_COUNT": 2.0,
            "BOX_COUNT": 27.0,
            "PLACE_ID": "ChIJb9CqdM0Z2jER49n5jq33AB0"
        },
        {
            "CAR_NUM": "CE01",
            "VISIT_ORDER": 8,
            "Y": 1.311143,
            "X": 103.861721,
            "ADDRESS_FULL": "31 Cavan Road Singapore 209857,Singapore,20  Little  India,31 CAVAN ROAD,  209857",
            "ZIP_CODE": "209857",
            "OPT_ARR_TIME_HM": "12:03",
            "EST_PROC_TIME": 7,
            "BOX_NUM": 1,
            "ORDER_VOLUME": 1.567,
            "OPEN_TIME": 720,
            "CLOSE_TIME": 960,
            "NM_COUNT": 1.0,
            "BOX_COUNT": 1.0,
            "PLACE_ID": "ChIJBUBEXckZ2jERmAp5b0A4isI"
        },
        {
            "CAR_NUM": "CE01",
            "VISIT_ORDER": 9,
            "Y": 1.311405,
            "X": 103.862492,
            "ADDRESS_FULL": "112, 112, Lavender Street 338728",
            "ZIP_CODE": "338728",
            "OPT_ARR_TIME_HM": "12:22",
            "EST_PROC_TIME": 7,
            "BOX_NUM": 1,
            "ORDER_VOLUME": 1.557,
            "OPEN_TIME": 720,
            "CLOSE_TIME": 900,
            "NM_COUNT": 1.0,
            "BOX_COUNT": 1.0,
            "PLACE_ID": "ChIJjfKSzssZ2jERs9f5jq33AB0"
        },
        {
            "CAR_NUM": "CE01",
            "VISIT_ORDER": 10,
            "Y": 1.311459,
            "X": 103.863626,
            "ADDRESS_FULL": "114 Lavender Street , CT HUB 2 #03-68,Singapore,33  Balestier  Toa  Payoh  Serangoon,114 LAVENDER STREET,  338729",
            "ZIP_CODE": "338729",
            "OPT_ARR_TIME_HM": "12:41",
            "EST_PROC_TIME": 10,
            "BOX_NUM": 11,
            "ORDER_VOLUME": 3.806,
            "OPEN_TIME": 720,
            "CLOSE_TIME": 1200,
            "NM_COUNT": 2.0,
            "BOX_COUNT": 12.0,
            "PLACE_ID": "ChIJSca84ssZ2jERQ9j5jq33AB0"
        },
        {
            "CAR_NUM": "CE01",
            "VISIT_ORDER": 11,
            "Y": 1.311459,
            "X": 103.863626,
            "ADDRESS_FULL": "114 Lavender Street #03-68,Singapore,33  Balestier  Toa  Payoh  Serangoon,114 LAVENDER STREET,  338729",
            "ZIP_CODE": "338729",
            "OPT_ARR_TIME_HM": "13:01",
            "EST_PROC_TIME": 7,
            "BOX_NUM": 1,
            "ORDER_VOLUME": 0.233,
            "OPEN_TIME": 720,
            "CLOSE_TIME": 1200,
            "NM_COUNT": 2.0,
            "BOX_COUNT": 12.0,
            "PLACE_ID": "ChIJSca84ssZ2jERQ9j5jq33AB0"
        },
        {
            "CAR_NUM": "CE01",
            "VISIT_ORDER": 12,
            "Y": 1.3113620000000001,
            "X": 103.866805,
            "ADDRESS_FULL": "103 Kallang Avenue #06-02,Singapore,33  Balestier  Toa  Payoh  Serangoon,103 KALLANG AVENUE,  339504",
            "ZIP_CODE": "339504",
            "OPT_ARR_TIME_HM": "13:22",
            "EST_PROC_TIME": 10,
            "BOX_NUM": 10,
            "ORDER_VOLUME": 15.57,
            "OPEN_TIME": 840,
            "CLOSE_TIME": 1140,
            "NM_COUNT": 1.0,
            "BOX_COUNT": 10.0,
            "PLACE_ID": "ChIJ2Z1OQcsZ2jERSYbcDEOnB-k"
        },
        {
            "CAR_NUM": "CE01",
            "VISIT_ORDER": 13,
            "Y": 1.314806,
            "X": 103.867244,
            "ADDRESS_FULL": "28 Kallang Place #03-07 Singapore, 339158,Singapore,33  Balestier  Toa  Payoh  Serangoon,28 KALLANG PLACE,  339158",
            "ZIP_CODE": "339158",
            "OPT_ARR_TIME_HM": "13:35",
            "EST_PROC_TIME": 7,
            "BOX_NUM": 1,
            "ORDER_VOLUME": 1.557,
            "OPEN_TIME": 780,
            "CLOSE_TIME": 1020,
            "NM_COUNT": 1.0,
            "BOX_COUNT": 1.0,
            "PLACE_ID": "ChIJtTL828wZ2jERytzqcKz3ABM"
        },
        {
            "CAR_NUM": "CE01",
            "VISIT_ORDER": 14,
            "Y": 1.315409,
            "X": 103.86749,
            "ADDRESS_FULL": "Blk 26 Kallang Place #05-07,Singapore,33  Balestier  Toa  Payoh  Serangoon,26 KALLANG PLACE,  339157",
            "ZIP_CODE": "339157",
            "OPT_ARR_TIME_HM": "13:44",
            "EST_PROC_TIME": 10,
            "BOX_NUM": 11,
            "ORDER_VOLUME": 13.079,
            "OPEN_TIME": 720,
            "CLOSE_TIME": 1260,
            "NM_COUNT": 1.0,
            "BOX_COUNT": 11.0,
            "PLACE_ID": "ChIJv9C_Mc0Z2jERM-L5jq33AB0"
        },
        {
            "CAR_NUM": "CE01",
            "VISIT_ORDER": 15,
            "Y": 1.316284,
            "X": 103.867902,
            "ADDRESS_FULL": "9 Kallang Place, #05-04,Singapore,33  Balestier  Toa  Payoh  Serangoon,9 KALLANG PLACE,  339154",
            "ZIP_CODE": "339154",
            "OPT_ARR_TIME_HM": "13:57",
            "EST_PROC_TIME": 14,
            "BOX_NUM": 24,
            "ORDER_VOLUME": 37.368,
            "OPEN_TIME": 720,
            "CLOSE_TIME": 900,
            "NM_COUNT": 1.0,
            "BOX_COUNT": 24.0,
            "PLACE_ID": "ChIJ7WRPyTIY2jERKt3qcKz3ABM"
        },
        {
            "CAR_NUM": "CE01",
            "VISIT_ORDER": 16,
            "Y": 1.3162399999999999,
            "X": 103.86654399999999,
            "ADDRESS_FULL": "16 Kallang Place #06-32/33, Singapore 339156,Singapore,33  Balestier  Toa  Payoh  Serangoon,16 KALLANG PLACE,  339156",
            "ZIP_CODE": "339156",
            "OPT_ARR_TIME_HM": "14:13",
            "EST_PROC_TIME": 8,
            "BOX_NUM": 2,
            "ORDER_VOLUME": 3.114,
            "OPEN_TIME": 720,
            "CLOSE_TIME": 1020,
            "NM_COUNT": 4.0,
            "BOX_COUNT": 30.0,
            "PLACE_ID": "ChIJQQ8qW80Z2jER1NzqcKz3ABM"
        },
        {
            "CAR_NUM": "CE01",
            "VISIT_ORDER": 17,
            "Y": 1.3162399999999999,
            "X": 103.86654399999999,
            "ADDRESS_FULL": "16 KALLANG PLACE, #03-08,Singapore,33  Balestier  Toa  Payoh  Serangoon,16 KALLANG PLACE,  339156",
            "ZIP_CODE": "339156",
            "OPT_ARR_TIME_HM": "14:21",
            "EST_PROC_TIME": 10,
            "BOX_NUM": 11,
            "ORDER_VOLUME": 14.762,
            "OPEN_TIME": 720,
            "CLOSE_TIME": 1020,
            "NM_COUNT": 4.0,
            "BOX_COUNT": 30.0,
            "PLACE_ID": "ChIJQQ8qW80Z2jER1NzqcKz3ABM"
        },
        {
            "CAR_NUM": "CE01",
            "VISIT_ORDER": 18,
            "Y": 1.3162399999999999,
            "X": 103.86654399999999,
            "ADDRESS_FULL": "16 KALLANG PLACE #01-21,Singapore,33  Balestier  Toa  Payoh  Serangoon,16 KALLANG PLACE,  339156",
            "ZIP_CODE": "339156",
            "OPT_ARR_TIME_HM": "14:31",
            "EST_PROC_TIME": 11,
            "BOX_NUM": 15,
            "ORDER_VOLUME": 23.355,
            "OPEN_TIME": 720,
            "CLOSE_TIME": 1020,
            "NM_COUNT": 4.0,
            "BOX_COUNT": 30.0,
            "PLACE_ID": "ChIJQQ8qW80Z2jER1NzqcKz3ABM"
        },
        {
            "CAR_NUM": "CE01",
            "VISIT_ORDER": 19,
            "Y": 1.3162399999999999,
            "X": 103.86654399999999,
            "ADDRESS_FULL": "16 KALLANG PLACE, #03-04,Singapore,33  Balestier  Toa  Payoh  Serangoon,16 KALLANG PLACE,  339156",
            "ZIP_CODE": "339156",
            "OPT_ARR_TIME_HM": "14:42",
            "EST_PROC_TIME": 8,
            "BOX_NUM": 2,
            "ORDER_VOLUME": 6.356,
            "OPEN_TIME": 720,
            "CLOSE_TIME": 1020,
            "NM_COUNT": 4.0,
            "BOX_COUNT": 30.0,
            "PLACE_ID": "ChIJQQ8qW80Z2jER1NzqcKz3ABM"
        },
        {
            "CAR_NUM": "CE05",
            "VISIT_ORDER": 5,
            "Y": 1.300139,
            "X": 103.848649,
            "ADDRESS_FULL": "10-25, 11, Sophia Road 228194",
            "ZIP_CODE": "228194",
            "OPT_ARR_TIME_HM": "11:22",
            "EST_PROC_TIME": 7,
            "BOX_NUM": 1,
            "ORDER_VOLUME": 1.557,
            "OPEN_TIME": 600,
            "CLOSE_TIME": 720,
            "NM_COUNT": 1.0,
            "BOX_COUNT": 1.0,
            "PLACE_ID": "ChIJe4Ev7rwZ2jERlhdIkPQIErY"
        },
        {
            "CAR_NUM": "CE05",
            "VISIT_ORDER": 6,
            "Y": 1.300626,
            "X": 103.849458,
            "ADDRESS_FULL": "35 Selegie Road, #02-16,Singapore,18  Middle  Road  Golden  Mile,35 SELEGIE ROAD,  188307",
            "ZIP_CODE": "188307",
            "OPT_ARR_TIME_HM": "12:01",
            "EST_PROC_TIME": 9,
            "BOX_NUM": 7,
            "ORDER_VOLUME": 14.112,
            "OPEN_TIME": 780,
            "CLOSE_TIME": 1080,
            "NM_COUNT": 2.0,
            "BOX_COUNT": 9.0,
            "PLACE_ID": "ChIJmU8cirwZ2jERpxJzWOazouk"
        },
        {
            "CAR_NUM": "CE05",
            "VISIT_ORDER": 7,
            "Y": 1.300626,
            "X": 103.849458,
            "ADDRESS_FULL": "35 SELEGIE ROAD, #02-16,  188307",
            "ZIP_CODE": "188307",
            "OPT_ARR_TIME_HM": "12:10",
            "EST_PROC_TIME": 8,
            "BOX_NUM": 2,
            "ORDER_VOLUME": 4.604,
            "OPEN_TIME": 780,
            "CLOSE_TIME": 1080,
            "NM_COUNT": 2.0,
            "BOX_COUNT": 9.0,
            "PLACE_ID": "ChIJmU8cirwZ2jERpxJzWOazouk"
        },
        {
            "CAR_NUM": "CE05",
            "VISIT_ORDER": 8,
            "Y": 1.300815,
            "X": 103.848866,
            "ADDRESS_FULL": "15 Sophia Road #12-31 Sophia, Residence 228196",
            "ZIP_CODE": "228196",
            "OPT_ARR_TIME_HM": "12:18",
            "EST_PROC_TIME": 7,
            "BOX_NUM": 1,
            "ORDER_VOLUME": 1.557,
            "OPEN_TIME": 720,
            "CLOSE_TIME": 900,
            "NM_COUNT": 1.0,
            "BOX_COUNT": 1.0,
            "PLACE_ID": "ChIJf_RAX7wZ2jERwcszpiHLjGk"
        },
        {
            "CAR_NUM": "CE05",
            "VISIT_ORDER": 9,
            "Y": 1.301251,
            "X": 103.851242,
            "ADDRESS_FULL": "-, 210, Middle Road 188994",
            "ZIP_CODE": "188994",
            "OPT_ARR_TIME_HM": "12:28",
            "EST_PROC_TIME": 7,
            "BOX_NUM": 1,
            "ORDER_VOLUME": 1.557,
            "OPEN_TIME": 720,
            "CLOSE_TIME": 900,
            "NM_COUNT": 1.0,
            "BOX_COUNT": 1.0,
            "PLACE_ID": "ChIJx992hLsZ2jERg8P5jq33AB0"
        },
        {
            "CAR_NUM": "CE05",
            "VISIT_ORDER": 10,
            "Y": 1.300287,
            "X": 103.85119300000001,
            "ADDRESS_FULL": "91 Bencoolen Street #01-27, Sunshine Plaza, 189652,Singapore,18  Middle  Road  Golden  Mile,91 BENCOOLEN STREET,  189652",
            "ZIP_CODE": "189652",
            "OPT_ARR_TIME_HM": "12:38",
            "EST_PROC_TIME": 9,
            "BOX_NUM": 7,
            "ORDER_VOLUME": 10.899,
            "OPEN_TIME": 720,
            "CLOSE_TIME": 900,
            "NM_COUNT": 1.0,
            "BOX_COUNT": 7.0,
            "PLACE_ID": "ChIJs-v5b7sZ2jERur7kcKz3ABM"
        },
        {
            "CAR_NUM": "CE05",
            "VISIT_ORDER": 11,
            "Y": 1.2996290000000001,
            "X": 103.854302,
            "ADDRESS_FULL": "201, VICTORIA STREET 188067",
            "ZIP_CODE": "188067",
            "OPT_ARR_TIME_HM": "12:52",
            "EST_PROC_TIME": 7,
            "BOX_NUM": 1,
            "ORDER_VOLUME": 1.557,
            "OPEN_TIME": 720,
            "CLOSE_TIME": 900,
            "NM_COUNT": 1.0,
            "BOX_COUNT": 1.0,
            "PLACE_ID": "ChIJx2uOwroZ2jERiMItEIzbns0"
        },
        {
            "CAR_NUM": "CE05",
            "VISIT_ORDER": 12,
            "Y": 1.3020260000000001,
            "X": 103.85364799999999,
            "ADDRESS_FULL": "60 Albert Street #05-01 OG Albert Complex,Singapore,18  Middle  Road  Golden  Mile,60 ALBERT STREET,  189969",
            "ZIP_CODE": "189969",
            "OPT_ARR_TIME_HM": "13:02",
            "EST_PROC_TIME": 8,
            "BOX_NUM": 4,
            "ORDER_VOLUME": 6.228,
            "OPEN_TIME": 720,
            "CLOSE_TIME": 900,
            "NM_COUNT": 1.0,
            "BOX_COUNT": 4.0,
            "PLACE_ID": "ChIJ0_SB2rsZ2jERKu3vcKz3ABM"
        },
        {
            "CAR_NUM": "CE05",
            "VISIT_ORDER": 13,
            "Y": 1.28983,
            "X": 103.849601,
            "ADDRESS_FULL": "1 NORTH BRIDGE ROAD #02-33 HIGH STREET CENTRE,Singapore,17  High  Street  Beach  Road  (part),1 NORTH BRIDGE ROAD,  179094",
            "ZIP_CODE": "179094",
            "OPT_ARR_TIME_HM": "13:19",
            "EST_PROC_TIME": 9,
            "BOX_NUM": 7,
            "ORDER_VOLUME": 22.267,
            "OPEN_TIME": 720,
            "CLOSE_TIME": 1140,
            "NM_COUNT": 2.0,
            "BOX_COUNT": 12.0,
            "PLACE_ID": "ChIJRbEel6AZ2jERA6H4jq33AB0"
        },
        {
            "CAR_NUM": "CE05",
            "VISIT_ORDER": 14,
            "Y": 1.28983,
            "X": 103.849601,
            "ADDRESS_FULL": "No 1 north bridge road, 01-08,high street center,singapore -179094,Singapore,17  High  Street  Beach  Road  (part),1 NORTH BRIDGE ROAD,  179094",
            "ZIP_CODE": "179094",
            "OPT_ARR_TIME_HM": "13:29",
            "EST_PROC_TIME": 8,
            "BOX_NUM": 5,
            "ORDER_VOLUME": 5.64,
            "OPEN_TIME": 720,
            "CLOSE_TIME": 1140,
            "NM_COUNT": 2.0,
            "BOX_COUNT": 12.0,
            "PLACE_ID": "ChIJRbEel6AZ2jERA6H4jq33AB0"
        },
        {
            "CAR_NUM": "CE05",
            "VISIT_ORDER": 15,
            "Y": 1.290668,
            "X": 103.846205,
            "ADDRESS_FULL": "Corinthians Asia Group Office, 3E RIVER VALLEY ROAD, Clarke Quay, #04-01 (Take lift from lift lobby E4 (located near carpark EXIT gantry) to level 4),Singapore,17  High  Street  Beach  Road  (part),3E RIVER VALLEY ROAD,  179024",
            "ZIP_CODE": "179024",
            "OPT_ARR_TIME_HM": "13:40",
            "EST_PROC_TIME": 8,
            "BOX_NUM": 4,
            "ORDER_VOLUME": 6.228,
            "OPEN_TIME": 720,
            "CLOSE_TIME": 900,
            "NM_COUNT": 1.0,
            "BOX_COUNT": 4.0,
            "PLACE_ID": "ChIJd_MiW6AZ2jERAtLkcKz3ABM"
        }
    ]
}